MANIFEST.in
README.rst
setup.py
version.py
src/cgcloud/__init__.py
src/cgcloud/toil/__init__.py
src/cgcloud/toil/toil_box.py
src/cgcloud/toil/toil_cluster.py
src/cgcloud/toil/test/__init__.py
src/cgcloud/toil/test/conftest.py
src/cgcloud/toil/test/test_toil.py
src/cgcloud_toil.egg-info/PKG-INFO
src/cgcloud_toil.egg-info/SOURCES.txt
src/cgcloud_toil.egg-info/dependency_links.txt
src/cgcloud_toil.egg-info/namespace_packages.txt
src/cgcloud_toil.egg-info/requires.txt
src/cgcloud_toil.egg-info/top_level.txt