Metadata-Version: 1.0
Name: cgcloud-toil
Version: 1.6.0a1.dev409
Summary: Setup and manage a toil and Apache Mesos cluster in EC2
Home-page: https://github.com/BD2KGenomics/cgcloud
Author: Christopher Ketchum
Author-email: cketchum@ucsc.edu
License: UNKNOWN
Platform: UNKNOWN
